tesserparsing/README.MD
tesserparsing/__init__.py
tesserparsing/requirements.txt
tesserparsing/thirdparty.json
tesserparsing-0.10.dist-info/LICENSE.rst
tesserparsing-0.10.dist-info/METADATA
tesserparsing-0.10.dist-info/WHEEL
tesserparsing-0.10.dist-info/top_level.txt
tesserparsing-0.10.dist-info/RECORD
