Metadata-Version: 2.1
Name: tesserparsing
Version: 0.10
Summary: Image Processing and Text Extraction with Tesseract - multiprocessing
Home-page: https://github.com/hansalemaos/tesserparsing
Author: Johannes Fischer
Author-email: aulasparticularesdealemaosp@gmail.com
License: MIT
Keywords: multiprocessing,tesseract
Classifier: Development Status :: 4 - Beta
Classifier: Programming Language :: Python :: 3 :: Only
Classifier: Programming Language :: Python :: 3.10
Classifier: Topic :: Software Development :: Libraries :: Python Modules
Classifier: Topic :: Utilities
License-File: LICENSE.rst
Requires-Dist: a-cv-imwrite-imread-plus
Requires-Dist: multiprocca
Requires-Dist: opencv-python
Requires-Dist: pandas
